[
  {
    "inputs": [
      {
        "internalType": "address",
        "name": "meme",
        "type": "address"
      },
      {
        "internalType": "address",
        "name": "user",
        "type": "address"
      },
      {
        "internalType": "uint256",
        "name": "count",
        "type": "uint256"
      },
      {
        "internalType": "bytes32[]",
        "name": "merkleProof",
        "type": "bytes32[]"
      }
    ],
    "name": "verify",
    "outputs": [
      {
        "internalType": "bool",
        "name": "verified",
        "type": "bool"
      }
    ],
    "stateMutability": "view",
    "type": "function"
  }
]
