[
  {
    "inputs": [
      {
        "internalType": "bytes",
        "name": "message",
        "type": "bytes"
      },
      {
        "internalType": "bytes",
        "name": "signature",
        "type": "bytes"
      }
    ],
    "name": "verify",
    "outputs": [
      {
        "components": [
          {
            "internalType": "address",
            "name": "token",
            "type": "address"
          },
          {
            "internalType": "address",
            "name": "user",
            "type": "address"
          },
          {
            "internalType": "uint256",
            "name": "count",
            "type": "uint256"
          },
          {
            "internalType": "uint256",
            "name": "timestamp",
            "type": "uint256"
          }
        ],
        "internalType": "struct IMemeWhitelist.WhitelistMessage",
        "name": "",
        "type": "tuple"
      }
    ],
    "stateMutability": "view",
    "type": "function"
  }
]
